equiface/__init__.py
equiface/constants.py
equiface/image_utils.py
equiface/logging_utils.py
equiface/verification.py
equiface-0.1.1.dist-info/licenses/LICENSE
equiface-0.1.1.dist-info/METADATA
equiface-0.1.1.dist-info/WHEEL
equiface-0.1.1.dist-info/entry_points.txt
equiface-0.1.1.dist-info/top_level.txt
equiface-0.1.1.dist-info/RECORD
